typety/__init__.py
typety-1.0.3.dist-info/WHEEL
typety-1.0.3.dist-info/METADATA
typety-1.0.3.dist-info/RECORD
