Metadata-Version: 2.1
Name: typety
Version: 1.0.3
Summary: A simple python packages that adds a typing effect to strings
Home-page: https://github.com/Dragonlord1005/typety
Author: Dragonlord1005
Requires-Python: >=3.8,<4.0
Classifier: Programming Language :: Python :: 3
Classifier: Programming Language :: Python :: 3.8
Classifier: Programming Language :: Python :: 3.9
Classifier: Topic :: Software Development :: Libraries :: Python Modules
Project-URL: Documentation, https://typety.readthedocs.io/
